{
  "title": "Intel’s Core Ultra 20000 Series: Efficiency Gains with Mixed Feedback ",
  "score": 34,
  "selftext": "[deleted]",
  "link_flair_text": "News",
  "id": "1gckx2u",
  "num_comments": 9,
  "created_utc": 1729948778,
  "permalink": "/r/wallstreetbets/comments/1gckx2u/intels_core_ultra_20000_series_efficiency_gains/",
  "url_overridden_by_dest": "",
  "comments": [
    {
      "id": "ltuhbnx",
      "score": 1,
      "body": "\n**User Report**| | | |\n:--|:--|:--|:--\n**Total Submissions** | 3 | **First Seen In WSB** | 2 days ago\n**Total Comments** | 0 | **Previous Best DD** | \n**Account Age** | 5 years | | \n\n[**Join WSB Discord**](http://discord.gg/wsbverse)",
      "permalink": "/r/wallstreetbets/comments/1gckx2u/intels_core_ultra_20000_series_efficiency_gains/ltuhbnx/",
      "created": 1729948781,
      "depth": 0,
      "replies": []
    },
    {
      "id": "ltutsoa",
      "score": 15,
      "body": "The fuck is this source",
      "permalink": "/r/wallstreetbets/comments/1gckx2u/intels_core_ultra_20000_series_efficiency_gains/ltutsoa/",
      "created": 1729953459,
      "depth": 0,
      "replies": []
    },
    {
      "id": "ltwi2ob",
      "score": 6,
      "body": "lolz @ \"mixed feedback\"\n\ni guess that's one way to spin it",
      "permalink": "/r/wallstreetbets/comments/1gckx2u/intels_core_ultra_20000_series_efficiency_gains/ltwi2ob/",
      "created": 1729973379,
      "depth": 0,
      "replies": []
    },
    {
      "id": "ltyq5dq",
      "score": 2,
      "body": "It's a fine CPU, not so great for gaming but OK for general workload. However, it's not great....and definitely not going to (re)gain market share from AMD..... Intel needs to get their 18A node into a winning competitive product. 2025, make or break.",
      "permalink": "/r/wallstreetbets/comments/1gckx2u/intels_core_ultra_20000_series_efficiency_gains/ltyq5dq/",
      "created": 1730004319,
      "depth": 0,
      "replies": []
    },
    {
      "id": "ltut897",
      "score": 2,
      "body": "I'd say it was AMDomination with Zen 5 with a sprinkling of wins for Arrowlake in blender or cinebench. I'm glad power is better now, but still beat out by Zen 5 on an older node. I think that's what I'm most disappointed in arrow lake, the best node, and only ho hum efficiency and performance. AMD will continue to take marketshare as a result.",
      "permalink": "/r/wallstreetbets/comments/1gckx2u/intels_core_ultra_20000_series_efficiency_gains/ltut897/",
      "created": 1729953255,
      "depth": 0,
      "replies": [
        {
          "id": "ltv5r02",
          "score": 6,
          "body": "Bagholders claim that Intel is competitive in pure CPU design. But if they are getting beat by AMD, using the same foundry, with a more advanced node that gives them a free ~10% headstart in speed... maybe their design groups aren't all that.",
          "permalink": "/r/wallstreetbets/comments/1gckx2u/intels_core_ultra_20000_series_efficiency_gains/ltv5r02/",
          "created": 1729957518,
          "depth": 1,
          "replies": []
        }
      ]
    },
    {
      "id": "ltuw7w6",
      "score": 0,
      "body": "🤔 interesting",
      "permalink": "/r/wallstreetbets/comments/1gckx2u/intels_core_ultra_20000_series_efficiency_gains/ltuw7w6/",
      "created": 1729954296,
      "depth": 0,
      "replies": []
    }
  ]
}